[
  {
    "id": "seed-1",
    "title": "There's Something Wrong in Finland",
    "subtitle": "Evidence from the North",
    "year": 2026,
    "status": "Upcoming",
    "shortDescription": "Found-footage and folklore-inspired stories across Finland. A 25-story anthology framed like recovered documents, interviews, and testimony.",
    "longDescription": "An anthology built to feel like a case file from Finland: twenty-five stories told through interviews, artifacts, and found footage so the supernatural stays uncomfortably real instead of spectacular.",
    "coverImageUrl": "/pictures/front.png",
    "slug": "theres-something-wrong-in-finland"
  }
]
